cloudmesh_multipass-4.1.4-py3.8-nspkg.pth
cloudmesh/multipass/Deploy.py
cloudmesh/multipass/Provider.py
cloudmesh/multipass/__init__.py
cloudmesh/multipass/__version__.py
cloudmesh/multipass/command/__init__.py
cloudmesh/multipass/command/multipass.py
cloudmesh_multipass-4.1.4.dist-info/LICENSE
cloudmesh_multipass-4.1.4.dist-info/METADATA
cloudmesh_multipass-4.1.4.dist-info/WHEEL
cloudmesh_multipass-4.1.4.dist-info/namespace_packages.txt
cloudmesh_multipass-4.1.4.dist-info/top_level.txt
cloudmesh_multipass-4.1.4.dist-info/RECORD
